patx/__init__.py
patx/core.py
patx/models.py
patx/py.typed
patx/data/E003.parquet
patx/data/__init__.py
patx-0.5.0.dist-info/METADATA
patx-0.5.0.dist-info/WHEEL
patx-0.5.0.dist-info/top_level.txt
patx-0.5.0.dist-info/RECORD
