Metadata-Version: 2.4
Name: patx
Version: 0.5.0
Summary: Pattern eXtraction for Time Series and Spatial Data
Author-email: Jonas Wolber <jonascw@web.de>
Maintainer-email: Jonas Wolber <jonascw@web.de>
License-Expression: MIT
Project-URL: Repository, https://github.com/Prgrmmrjns/patX
Keywords: time-series,spatial-data,feature-engineering,pattern-extraction,machine-learning,optimization,polynomial-patterns
Classifier: Development Status :: 3 - Alpha
Classifier: Intended Audience :: Developers
Classifier: Intended Audience :: Science/Research
Classifier: Operating System :: OS Independent
Classifier: Programming Language :: Python :: 3
Classifier: Programming Language :: Python :: 3.11
Classifier: Programming Language :: Python :: 3.12
Classifier: Programming Language :: Python :: 3.13
Classifier: Topic :: Scientific/Engineering :: Artificial Intelligence
Classifier: Topic :: Scientific/Engineering :: Information Analysis
Classifier: Topic :: Software Development :: Libraries :: Python Modules
Requires-Python: >=3.11
Requires-Dist: numpy
Requires-Dist: pandas
Requires-Dist: scikit-learn
Requires-Dist: optuna
Requires-Dist: lightgbm
Requires-Dist: pywavelets
Requires-Dist: scipy
